{
  "script_version": "v10_history_guard_20260513",
  "updated_at": "2026-05-25T13:07:30+00:00",
  "expected_trade_date": "2026-05-25",
  "stale_codes": [],
  "items": {
    "014362": {
      "code": "014362",
      "name": "睿远稳进配置两年持有混合A",
      "nav": 1.1985,
      "date": "2026-05-25",
      "date_time": "2026-05-25",
      "daily_pct": 0.11,
      "source": "东方财富JSON最新净值",
      "estimated": false,
      "official": true,
      "ok": true,
      "date_ok": true,
      "expected_trade_date": "2026-05-25",
      "script_version": "v10_history_guard_20260513",
      "diagnosis": "script=v10_history_guard_20260513; history=东方财富F10历史净值; official_candidates=东方财富JSON最新净值:2026-05-25:1.1985 | 东方财富F10最新净值:2026-05-25:1.1985 | AKShare fund_open_fund_info_em:2026-05-25:1.1985 | 天天基金fundgz确认净值:2026-05-22:1.1972; reference_only=天天基金fundgz估算参考:2026-05-25:1.1961(参考) | 新浪财经fu_估算参考:2026-05-25:1.1985(参考); history_guard=merged_old_history old_len=1060 fetched_len=20 merged_len=1061"
    },
    "001511": {
      "code": "001511",
      "name": "兴全新视野定期开放混合型发起式",
      "nav": 2.536,
      "date": "2026-05-25",
      "date_time": "2026-05-25",
      "daily_pct": 0.88,
      "source": "东方财富JSON最新净值",
      "estimated": false,
      "official": true,
      "ok": true,
      "date_ok": true,
      "expected_trade_date": "2026-05-25",
      "script_version": "v10_history_guard_20260513",
      "diagnosis": "script=v10_history_guard_20260513; history=东方财富F10历史净值; official_candidates=东方财富JSON最新净值:2026-05-25:2.536 | 东方财富F10最新净值:2026-05-25:2.536 | AKShare fund_open_fund_info_em:2026-05-22:2.514 | 天天基金fundgz确认净值:2026-05-22:2.514; reference_only=天天基金fundgz估算参考:2026-05-25:2.5235(参考) | 新浪财经fu_估算参考:2026-05-25:2.5522(参考); history_guard=merged_old_history old_len=1353 fetched_len=20 merged_len=1354"
    },
    "007120": {
      "code": "007120",
      "name": "睿远成长价值混合C",
      "nav": 2.6122,
      "date": "2026-05-25",
      "date_time": "2026-05-25",
      "daily_pct": 2.96,
      "source": "东方财富JSON最新净值",
      "estimated": false,
      "official": true,
      "ok": true,
      "date_ok": true,
      "expected_trade_date": "2026-05-25",
      "script_version": "v10_history_guard_20260513",
      "diagnosis": "script=v10_history_guard_20260513; history=东方财富F10历史净值; official_candidates=东方财富JSON最新净值:2026-05-25:2.6122 | 东方财富F10最新净值:2026-05-25:2.6122 | AKShare fund_open_fund_info_em:2026-05-25:2.6122 | 天天基金fundgz确认净值:2026-05-22:2.537; reference_only=天天基金fundgz估算参考:2026-05-25:2.6062(参考) | 新浪财经fu_估算参考:2026-05-25:2.6039(参考); history_guard=merged_old_history old_len=1353 fetched_len=20 merged_len=1354"
    },
    "169101": {
      "code": "169101",
      "name": "东方红睿丰混合",
      "nav": 2.577,
      "date": "2026-05-25",
      "date_time": "2026-05-25",
      "daily_pct": 2.38,
      "source": "东方财富JSON最新净值",
      "estimated": false,
      "official": true,
      "ok": true,
      "date_ok": true,
      "expected_trade_date": "2026-05-25",
      "script_version": "v10_history_guard_20260513",
      "diagnosis": "script=v10_history_guard_20260513; history=东方财富F10历史净值; official_candidates=东方财富JSON最新净值:2026-05-25:2.577 | 东方财富F10最新净值:2026-05-25:2.577 | AKShare fund_open_fund_info_em:2026-05-22:2.517 | 天天基金fundgz确认净值:2026-05-22:2.517; reference_only=天天基金fundgz估算参考:2026-05-25:2.5923(参考) | 新浪财经fu_估算参考:2026-05-25:2.6009(参考); history_guard=merged_old_history old_len=27 fetched_len=20 merged_len=28; WARNING: history seems short len=28 first=2026-04-13"
    },
    "007119": {
      "code": "007119",
      "name": "睿远成长价值混合A",
      "nav": 2.6881,
      "date": "2026-05-25",
      "date_time": "2026-05-25",
      "daily_pct": 2.96,
      "source": "东方财富JSON最新净值",
      "estimated": false,
      "official": true,
      "ok": true,
      "date_ok": true,
      "expected_trade_date": "2026-05-25",
      "script_version": "v10_history_guard_20260513",
      "diagnosis": "script=v10_history_guard_20260513; history=东方财富F10历史净值; official_candidates=东方财富JSON最新净值:2026-05-25:2.6881 | 东方财富F10最新净值:2026-05-25:2.6881 | AKShare fund_open_fund_info_em:2026-05-25:2.6881 | 天天基金fundgz确认净值:2026-05-22:2.6107; reference_only=天天基金fundgz估算参考:2026-05-25:2.6819(参考) | 新浪财经fu_估算参考:2026-05-25:2.6796(参考); history_guard=merged_old_history old_len=27 fetched_len=20 merged_len=28; WARNING: history seems short len=28 first=2026-04-13"
    },
    "006608": {
      "code": "006608",
      "name": "泓德研究优选混合",
      "nav": 1.5882,
      "date": "2026-05-25",
      "date_time": "2026-05-25",
      "daily_pct": 1.13,
      "source": "东方财富JSON最新净值",
      "estimated": false,
      "official": true,
      "ok": true,
      "date_ok": true,
      "expected_trade_date": "2026-05-25",
      "script_version": "v10_history_guard_20260513",
      "diagnosis": "script=v10_history_guard_20260513; history=东方财富F10历史净值; official_candidates=东方财富JSON最新净值:2026-05-25:1.5882 | 东方财富F10最新净值:2026-05-25:1.5882 | AKShare fund_open_fund_info_em:2026-05-22:1.5704 | 天天基金fundgz确认净值:2026-05-22:1.5704; reference_only=天天基金fundgz估算参考:2026-05-25:1.5925(参考) | 新浪财经fu_估算参考:2026-05-25:1.5954(参考); history_guard=merged_old_history old_len=27 fetched_len=20 merged_len=28; WARNING: history seems short len=28 first=2026-04-13"
    },
    "163417": {
      "code": "163417",
      "name": "兴全合宜灵活配置混合(LOF)A",
      "nav": 2.2334,
      "date": "2026-05-25",
      "date_time": "2026-05-25",
      "daily_pct": 0.84,
      "source": "东方财富JSON最新净值",
      "estimated": false,
      "official": true,
      "ok": true,
      "date_ok": true,
      "expected_trade_date": "2026-05-25",
      "script_version": "v10_history_guard_20260513",
      "diagnosis": "script=v10_history_guard_20260513; history=东方财富F10历史净值; official_candidates=东方财富JSON最新净值:2026-05-25:2.2334 | 东方财富F10最新净值:2026-05-25:2.2334 | AKShare fund_open_fund_info_em:2026-05-22:2.2147 | 天天基金fundgz确认净值:2026-05-22:2.2147; reference_only=天天基金fundgz估算参考:2026-05-25:2.2338(参考) | 新浪财经fu_估算参考:2026-05-25:2.2179(参考); history_guard=merged_old_history old_len=27 fetched_len=20 merged_len=28; WARNING: history seems short len=28 first=2026-04-13"
    },
    "010340": {
      "code": "010340",
      "name": "易方达高质量严选三年持有混合",
      "nav": 1.1042,
      "date": "2026-05-25",
      "date_time": "2026-05-25",
      "daily_pct": 1.87,
      "source": "东方财富JSON最新净值",
      "estimated": false,
      "official": true,
      "ok": true,
      "date_ok": true,
      "expected_trade_date": "2026-05-25",
      "script_version": "v10_history_guard_20260513",
      "diagnosis": "script=v10_history_guard_20260513; history=东方财富F10历史净值; official_candidates=东方财富JSON最新净值:2026-05-25:1.1042 | 东方财富F10最新净值:2026-05-25:1.1042 | AKShare fund_open_fund_info_em:2026-05-25:1.1042 | 天天基金fundgz确认净值:2026-05-22:1.0839; reference_only=天天基金fundgz估算参考:2026-05-25:1.0985(参考) | 新浪财经fu_估算参考:2026-05-25:1.085(参考); history_guard=merged_old_history old_len=27 fetched_len=20 merged_len=28; WARNING: history seems short len=28 first=2026-04-13"
    },
    "010273": {
      "code": "010273",
      "name": "嘉实价值长青混合A",
      "nav": 0.9736,
      "date": "2026-05-25",
      "date_time": "2026-05-25",
      "daily_pct": 0.14,
      "source": "东方财富JSON最新净值",
      "estimated": false,
      "official": true,
      "ok": true,
      "date_ok": true,
      "expected_trade_date": "2026-05-25",
      "script_version": "v10_history_guard_20260513",
      "diagnosis": "script=v10_history_guard_20260513; history=东方财富F10历史净值; official_candidates=东方财富JSON最新净值:2026-05-25:0.9736 | 东方财富F10最新净值:2026-05-25:0.9736 | AKShare fund_open_fund_info_em:2026-05-22:0.9722 | 天天基金fundgz确认净值:2026-05-22:0.9722; reference_only=天天基金fundgz估算参考:2026-05-25:0.9742(参考) | 新浪财经fu_估算参考:2026-05-25:0.9724(参考); history_guard=merged_old_history old_len=27 fetched_len=20 merged_len=28; WARNING: history seems short len=28 first=2026-04-13"
    },
    "010186": {
      "code": "010186",
      "name": "嘉实核心成长混合A",
      "nav": 0.8933,
      "date": "2026-05-25",
      "date_time": "2026-05-25",
      "daily_pct": 1.71,
      "source": "东方财富JSON最新净值",
      "estimated": false,
      "official": true,
      "ok": true,
      "date_ok": true,
      "expected_trade_date": "2026-05-25",
      "script_version": "v10_history_guard_20260513",
      "diagnosis": "script=v10_history_guard_20260513; history=东方财富F10历史净值; official_candidates=东方财富JSON最新净值:2026-05-25:0.8933 | 东方财富F10最新净值:2026-05-25:0.8933 | AKShare fund_open_fund_info_em:2026-05-22:0.8783 | 天天基金fundgz确认净值:2026-05-22:0.8783; reference_only=天天基金fundgz估算参考:2026-05-25:0.8872(参考) | 新浪财经fu_估算参考:2026-05-25:0.899(参考); history_guard=merged_old_history old_len=1303 fetched_len=20 merged_len=1304"
    },
    "010027": {
      "code": "010027",
      "name": "景顺长城核心中景一年持有期混合",
      "nav": 0.9218,
      "date": "2026-05-25",
      "date_time": "2026-05-25",
      "daily_pct": 2.31,
      "source": "东方财富JSON最新净值",
      "estimated": false,
      "official": true,
      "ok": true,
      "date_ok": true,
      "expected_trade_date": "2026-05-25",
      "script_version": "v10_history_guard_20260513",
      "diagnosis": "script=v10_history_guard_20260513; history=东方财富F10历史净值; official_candidates=东方财富JSON最新净值:2026-05-25:0.9218 | 东方财富F10最新净值:2026-05-25:0.9218 | AKShare fund_open_fund_info_em:2026-05-22:0.901 | 天天基金fundgz确认净值:2026-05-22:0.901; reference_only=天天基金fundgz估算参考:2026-05-25:0.9117(参考) | 新浪财经fu_估算参考:2026-05-25:0.9163(参考); history_guard=merged_old_history old_len=1292 fetched_len=20 merged_len=1293"
    },
    "501054": {
      "code": "501054",
      "name": "东方红睿泽三年定开混合A",
      "nav": 1.7462,
      "date": "2026-05-25",
      "date_time": "2026-05-25",
      "daily_pct": 2.39,
      "source": "东方财富JSON最新净值",
      "estimated": false,
      "official": true,
      "ok": true,
      "date_ok": true,
      "expected_trade_date": "2026-05-25",
      "script_version": "v10_history_guard_20260513",
      "diagnosis": "script=v10_history_guard_20260513; history=东方财富F10历史净值; official_candidates=东方财富JSON最新净值:2026-05-25:1.7462 | 东方财富F10最新净值:2026-05-25:1.7462 | AKShare fund_open_fund_info_em:2026-05-22:1.7055 | 天天基金fundgz确认净值:2026-05-22:1.7055; reference_only=天天基金fundgz估算参考:2026-05-25:1.7548(参考) | 新浪财经fu_估算参考:2026-05-25:1.758(参考); history_guard=merged_old_history old_len=27 fetched_len=20 merged_len=28; WARNING: history seems short len=28 first=2026-04-13"
    },
    "011006": {
      "code": "011006",
      "name": "工银圆丰三年持有期混合",
      "nav": 0.7867,
      "date": "2026-05-25",
      "date_time": "2026-05-25",
      "daily_pct": 0.81,
      "source": "东方财富JSON最新净值",
      "estimated": false,
      "official": true,
      "ok": true,
      "date_ok": true,
      "expected_trade_date": "2026-05-25",
      "script_version": "v10_history_guard_20260513",
      "diagnosis": "script=v10_history_guard_20260513; history=东方财富F10历史净值; official_candidates=东方财富JSON最新净值:2026-05-25:0.7867 | 东方财富F10最新净值:2026-05-25:0.7867 | AKShare fund_open_fund_info_em:2026-05-25:0.7867 | 天天基金fundgz确认净值:2026-05-22:0.7804; reference_only=天天基金fundgz估算参考:2026-05-25:0.7879(参考) | 新浪财经fu_估算参考:2026-05-25:0.7996(参考); history_guard=merged_old_history old_len=1255 fetched_len=20 merged_len=1256"
    },
    "501049": {
      "code": "501049",
      "name": "东方红睿玺三年定开混合A",
      "nav": 0.906,
      "date": "2026-05-25",
      "date_time": "2026-05-25",
      "daily_pct": -0.72,
      "source": "东方财富JSON最新净值",
      "estimated": false,
      "official": true,
      "ok": true,
      "date_ok": true,
      "expected_trade_date": "2026-05-25",
      "script_version": "v10_history_guard_20260513",
      "diagnosis": "script=v10_history_guard_20260513; history=东方财富F10历史净值; official_candidates=东方财富JSON最新净值:2026-05-25:0.906 | 东方财富F10最新净值:2026-05-25:0.906 | AKShare fund_open_fund_info_em:2026-05-22:0.9126 | 天天基金fundgz确认净值:2026-05-22:0.9126; reference_only=天天基金fundgz估算参考:2026-05-25:0.8988(参考) | 新浪财经fu_估算参考:2026-05-25:0.9025(参考); history_guard=merged_old_history old_len=1353 fetched_len=20 merged_len=1354"
    }
  }
}